tests/__init__.py
tests/test_topsis.py
topsis/__init__.py
topsis/topsis.py
Topsis_102366002_Krishna_Arora-1.0.0.dist-info/METADATA
Topsis_102366002_Krishna_Arora-1.0.0.dist-info/WHEEL
Topsis_102366002_Krishna_Arora-1.0.0.dist-info/entry_points.txt
Topsis_102366002_Krishna_Arora-1.0.0.dist-info/top_level.txt
Topsis_102366002_Krishna_Arora-1.0.0.dist-info/RECORD
